{
	"animations": [
		{
			"offsets": [
				118,
				21
			],
			"loop": false,
			"fps": 24,
			"anim": "singLEFT",
			"indices": [],
			"name": "right"
		},
		{
			"offsets": [
				116,
				-56
			],
			"loop": false,
			"fps": 24,
			"anim": "singDOWN",
			"indices": [],
			"name": "down"
		},
		{
			"offsets": [
				-151,
				268
			],
			"loop": false,
			"fps": 24,
			"anim": "singUP",
			"indices": [],
			"name": "up"
		},
		{
			"offsets": [
				-103,
				65
			],
			"loop": false,
			"fps": 24,
			"anim": "singRIGHT",
			"indices": [],
			"name": "left"
		},
		{
			"loop": true,
			"offsets": [
				0,
				0
			],
			"anim": "idle-loop",
			"fps": 24,
			"name": "idle",
			"indices": [
				10,
				11,
				12,
				13
			]
		},
		{
			"loop": true,
			"offsets": [
				118,
				21
			],
			"anim": "singLEFT-loop",
			"fps": 24,
			"name": "right",
			"indices": [
				10,
				11,
				12,
				13
			]
		},
		{
			"loop": true,
			"offsets": [
				116,
				-56
			],
			"anim": "singDOWN-loop",
			"fps": 24,
			"name": "down",
			"indices": [
				10,
				11,
				12,
				13
			]
		},
		{
			"loop": true,
			"offsets": [
				-151,
				268
			],
			"anim": "singUP-loop",
			"fps": 24,
			"name": "up",
			"indices": [
				10,
				11,
				12,
				13
			]
		},
		{
			"loop": true,
			"offsets": [
				-103,
				65
			],
			"anim": "singRIGHT-loop",
			"fps": 24,
			"name": "left",
			"indices": [
				10,
				11,
				12,
				13
			]
		},
		{
			"loop": false,
			"offsets": [
				0,
				0
			],
			"anim": "idle",
			"fps": 24,
			"name": "idle",
			"indices": []
		},
		{
			"loop": false,
			"offsets": [
				213,
				118
			],
			"anim": "yudodis",
			"fps": 24,
			"name": "y u do dis",
			"indices": []
		}
	],
	"no_antialiasing": false,
	"image": "characters/internet/spodr_men",
	"position": [
		-50,
		350
	],
	"healthicon": "spooder",
	"flip_x": false,
	"healthbar_colors": [
		254,
		0,
		0
	],
	"camera_position": [
		0,
		0
	],
	"sing_duration": 4,
	"scale": 1
}