<?xml version="1.0" encoding="utf-8"?>
<TextureAtlas imagePath="owned.png">
	<!-- Created with Adobe Animate version 22.0.5.191 -->
	<!-- http://www.adobe.com/products/animate.html -->
	<SubTexture name="shot instance 10000" x="10" y="10" width="641" height="360"/>
	<SubTexture name="shot instance 10001" x="671" y="10" width="640" height="360" frameX="0" frameY="0" frameWidth="641" frameHeight="360"/>
	<SubTexture name="shot instance 10002" x="671" y="10" width="640" height="360" frameX="0" frameY="0" frameWidth="641" frameHeight="360"/>
	<SubTexture name="shot instance 10003" x="1331" y="10" width="640" height="360" frameX="0" frameY="0" frameWidth="641" frameHeight="360"/>
	<SubTexture name="shot instance 10004" x="1991" y="10" width="640" height="360" frameX="0" frameY="0" frameWidth="641" frameHeight="360"/>
	<SubTexture name="shot instance 10005" x="2651" y="10" width="640" height="360" frameX="0" frameY="0" frameWidth="641" frameHeight="360"/>
	<SubTexture name="shot instance 10006" x="3311" y="10" width="640" height="360" frameX="0" frameY="0" frameWidth="641" frameHeight="360"/>
	<SubTexture name="shot instance 10007" x="3971" y="10" width="640" height="360" frameX="0" frameY="0" frameWidth="641" frameHeight="360"/>
	<SubTexture name="shot instance 10008" x="3971" y="10" width="640" height="360" frameX="0" frameY="0" frameWidth="641" frameHeight="360"/>
	<SubTexture name="shot instance 10009" x="4631" y="10" width="640" height="360" frameX="0" frameY="0" frameWidth="641" frameHeight="360"/>
	<SubTexture name="shot instance 10010" x="5291" y="10" width="640" height="360" frameX="0" frameY="0" frameWidth="641" frameHeight="360"/>
	<SubTexture name="shot instance 10011" x="5951" y="10" width="640" height="360" frameX="0" frameY="0" frameWidth="641" frameHeight="360"/>
	<SubTexture name="shot instance 10012" x="6611" y="10" width="640" height="360" frameX="0" frameY="0" frameWidth="641" frameHeight="360"/>
	<SubTexture name="shot instance 10013" x="7271" y="10" width="640" height="360" frameX="0" frameY="0" frameWidth="641" frameHeight="360"/>
	<SubTexture name="shot instance 10014" x="7271" y="10" width="640" height="360" frameX="0" frameY="0" frameWidth="641" frameHeight="360"/>
	<SubTexture name="shot instance 10015" x="10" y="390" width="640" height="360" frameX="0" frameY="0" frameWidth="641" frameHeight="360"/>
	<SubTexture name="shot instance 10016" x="670" y="390" width="640" height="360" frameX="0" frameY="0" frameWidth="641" frameHeight="360"/>
	<SubTexture name="shot instance 10017" x="1330" y="390" width="640" height="360" frameX="0" frameY="0" frameWidth="641" frameHeight="360"/>
	<SubTexture name="shot instance 10018" x="1990" y="390" width="640" height="360" frameX="0" frameY="0" frameWidth="641" frameHeight="360"/>
	<SubTexture name="shot instance 10019" x="2650" y="390" width="640" height="360" frameX="0" frameY="0" frameWidth="641" frameHeight="360"/>
	<SubTexture name="shot instance 10020" x="2650" y="390" width="640" height="360" frameX="0" frameY="0" frameWidth="641" frameHeight="360"/>
	<SubTexture name="shot instance 10021" x="3310" y="390" width="640" height="360" frameX="0" frameY="0" frameWidth="641" frameHeight="360"/>
	<SubTexture name="shot instance 10022" x="3970" y="390" width="640" height="360" frameX="0" frameY="0" frameWidth="641" frameHeight="360"/>
	<SubTexture name="shot instance 10023" x="4630" y="390" width="640" height="360" frameX="0" frameY="0" frameWidth="641" frameHeight="360"/>
	<SubTexture name="shot instance 10024" x="5290" y="390" width="640" height="360" frameX="0" frameY="0" frameWidth="641" frameHeight="360"/>
	<SubTexture name="shot instance 10025" x="5950" y="390" width="640" height="360" frameX="0" frameY="0" frameWidth="641" frameHeight="360"/>
	<SubTexture name="shot instance 10026" x="5950" y="390" width="640" height="360" frameX="0" frameY="0" frameWidth="641" frameHeight="360"/>
	<SubTexture name="shot instance 10027" x="6610" y="390" width="640" height="360" frameX="0" frameY="0" frameWidth="641" frameHeight="360"/>
	<SubTexture name="shot instance 10028" x="7270" y="390" width="640" height="360" frameX="0" frameY="0" frameWidth="641" frameHeight="360"/>
	<SubTexture name="shot instance 10029" x="10" y="770" width="640" height="360" frameX="0" frameY="0" frameWidth="641" frameHeight="360"/>
	<SubTexture name="shot instance 10030" x="670" y="770" width="640" height="360" frameX="0" frameY="0" frameWidth="641" frameHeight="360"/>
	<SubTexture name="shot instance 10031" x="1330" y="770" width="640" height="360" frameX="0" frameY="0" frameWidth="641" frameHeight="360"/>
	<SubTexture name="shot instance 10032" x="1330" y="770" width="640" height="360" frameX="0" frameY="0" frameWidth="641" frameHeight="360"/>
	<SubTexture name="shot instance 10033" x="1990" y="770" width="640" height="360" frameX="0" frameY="0" frameWidth="641" frameHeight="360"/>
	<SubTexture name="shot instance 10034" x="2650" y="770" width="640" height="360" frameX="0" frameY="0" frameWidth="641" frameHeight="360"/>
	<SubTexture name="shot instance 10035" x="3310" y="770" width="640" height="360" frameX="0" frameY="0" frameWidth="641" frameHeight="360"/>
	<SubTexture name="shot instance 10036" x="3970" y="770" width="640" height="360" frameX="0" frameY="0" frameWidth="641" frameHeight="360"/>
	<SubTexture name="shot instance 10037" x="4630" y="770" width="640" height="360" frameX="0" frameY="0" frameWidth="641" frameHeight="360"/>
	<SubTexture name="shot instance 10038" x="4630" y="770" width="640" height="360" frameX="0" frameY="0" frameWidth="641" frameHeight="360"/>
	<SubTexture name="shot instance 10039" x="5290" y="770" width="640" height="360" frameX="0" frameY="0" frameWidth="641" frameHeight="360"/>
	<SubTexture name="shot instance 10040" x="5950" y="770" width="640" height="360" frameX="0" frameY="0" frameWidth="641" frameHeight="360"/>
	<SubTexture name="shot instance 10041" x="6610" y="770" width="640" height="360" frameX="0" frameY="0" frameWidth="641" frameHeight="360"/>
	<SubTexture name="shot instance 10042" x="7270" y="770" width="640" height="360" frameX="0" frameY="0" frameWidth="641" frameHeight="360"/>
	<SubTexture name="shot instance 10043" x="10" y="1150" width="640" height="360" frameX="0" frameY="0" frameWidth="641" frameHeight="360"/>
	<SubTexture name="shot instance 10044" x="10" y="1150" width="640" height="360" frameX="0" frameY="0" frameWidth="641" frameHeight="360"/>
	<SubTexture name="shot instance 10045" x="670" y="1150" width="640" height="360" frameX="0" frameY="0" frameWidth="641" frameHeight="360"/>
	<SubTexture name="shot instance 10046" x="1330" y="1150" width="640" height="360" frameX="0" frameY="0" frameWidth="641" frameHeight="360"/>
	<SubTexture name="shot instance 10047" x="1990" y="1150" width="640" height="360" frameX="0" frameY="0" frameWidth="641" frameHeight="360"/>
	<SubTexture name="shot instance 10048" x="2650" y="1150" width="640" height="360" frameX="0" frameY="0" frameWidth="641" frameHeight="360"/>
	<SubTexture name="shot instance 10049" x="3310" y="1150" width="640" height="360" frameX="0" frameY="0" frameWidth="641" frameHeight="360"/>
	<SubTexture name="shot instance 10050" x="3310" y="1150" width="640" height="360" frameX="0" frameY="0" frameWidth="641" frameHeight="360"/>
	<SubTexture name="shot instance 10051" x="3970" y="1150" width="640" height="360" frameX="0" frameY="0" frameWidth="641" frameHeight="360"/>
	<SubTexture name="shot instance 10052" x="4630" y="1150" width="640" height="360" frameX="0" frameY="0" frameWidth="641" frameHeight="360"/>
	<SubTexture name="shot instance 10053" x="5290" y="1150" width="640" height="360" frameX="0" frameY="0" frameWidth="641" frameHeight="360"/>
	<SubTexture name="shot instance 10054" x="5950" y="1150" width="640" height="360" frameX="0" frameY="0" frameWidth="641" frameHeight="360"/>
	<SubTexture name="shot instance 10055" x="6610" y="1150" width="640" height="360" frameX="0" frameY="0" frameWidth="641" frameHeight="360"/>
	<SubTexture name="shot instance 10056" x="6610" y="1150" width="640" height="360" frameX="0" frameY="0" frameWidth="641" frameHeight="360"/>
	<SubTexture name="shot instance 10057" x="7270" y="1150" width="640" height="360" frameX="0" frameY="0" frameWidth="641" frameHeight="360"/>
	<SubTexture name="shot instance 10058" x="10" y="1530" width="640" height="360" frameX="0" frameY="0" frameWidth="641" frameHeight="360"/>
	<SubTexture name="shot instance 10059" x="670" y="1530" width="640" height="360" frameX="0" frameY="0" frameWidth="641" frameHeight="360"/>
	<SubTexture name="shot instance 10060" x="1330" y="1530" width="640" height="360" frameX="0" frameY="0" frameWidth="641" frameHeight="360"/>
	<SubTexture name="shot instance 10061" x="1990" y="1530" width="640" height="360" frameX="0" frameY="0" frameWidth="641" frameHeight="360"/>
	<SubTexture name="shot instance 10062" x="1990" y="1530" width="640" height="360" frameX="0" frameY="0" frameWidth="641" frameHeight="360"/>
	<SubTexture name="shot instance 10063" x="2650" y="1530" width="640" height="360" frameX="0" frameY="0" frameWidth="641" frameHeight="360"/>
	<SubTexture name="shot instance 10064" x="3310" y="1530" width="640" height="360" frameX="0" frameY="0" frameWidth="641" frameHeight="360"/>
	<SubTexture name="shot instance 10065" x="3970" y="1530" width="640" height="360" frameX="0" frameY="0" frameWidth="641" frameHeight="360"/>
	<SubTexture name="shot instance 10066" x="4630" y="1530" width="640" height="360" frameX="0" frameY="0" frameWidth="641" frameHeight="360"/>
	<SubTexture name="shot instance 10067" x="5290" y="1530" width="640" height="360" frameX="0" frameY="0" frameWidth="641" frameHeight="360"/>
	<SubTexture name="shot instance 10068" x="5290" y="1530" width="640" height="360" frameX="0" frameY="0" frameWidth="641" frameHeight="360"/>
	<SubTexture name="shot instance 10069" x="5950" y="1530" width="640" height="360" frameX="0" frameY="0" frameWidth="641" frameHeight="360"/>
	<SubTexture name="shot instance 10070" x="6610" y="1530" width="640" height="360" frameX="0" frameY="0" frameWidth="641" frameHeight="360"/>
	<SubTexture name="shot instance 10071" x="7270" y="1530" width="640" height="360" frameX="0" frameY="0" frameWidth="641" frameHeight="360"/>
	<SubTexture name="shot instance 10072" x="10" y="1910" width="640" height="360" frameX="0" frameY="0" frameWidth="641" frameHeight="360"/>
	<SubTexture name="shot instance 10073" x="670" y="1910" width="640" height="360" frameX="0" frameY="0" frameWidth="641" frameHeight="360"/>
	<SubTexture name="shot instance 10074" x="1330" y="1910" width="640" height="360" frameX="0" frameY="0" frameWidth="641" frameHeight="360"/>
	<SubTexture name="shot instance 10075" x="1330" y="1910" width="640" height="360" frameX="0" frameY="0" frameWidth="641" frameHeight="360"/>
	<SubTexture name="shot instance 10076" x="1990" y="1910" width="640" height="360" frameX="0" frameY="0" frameWidth="641" frameHeight="360"/>
	<SubTexture name="shot instance 10077" x="2650" y="1910" width="640" height="360" frameX="0" frameY="0" frameWidth="641" frameHeight="360"/>
	<SubTexture name="shot instance 10078" x="3310" y="1910" width="640" height="360" frameX="0" frameY="0" frameWidth="641" frameHeight="360"/>
	<SubTexture name="shot instance 10079" x="3970" y="1910" width="640" height="360" frameX="0" frameY="0" frameWidth="641" frameHeight="360"/>
	<SubTexture name="shot instance 10080" x="4630" y="1910" width="640" height="360" frameX="0" frameY="0" frameWidth="641" frameHeight="360"/>
	<SubTexture name="shot instance 10081" x="4630" y="1910" width="640" height="360" frameX="0" frameY="0" frameWidth="641" frameHeight="360"/>
	<SubTexture name="shot instance 10082" x="5290" y="1910" width="640" height="360" frameX="0" frameY="0" frameWidth="641" frameHeight="360"/>
	<SubTexture name="shot instance 10083" x="5950" y="1910" width="640" height="360" frameX="0" frameY="0" frameWidth="641" frameHeight="360"/>
	<SubTexture name="shot instance 10084" x="6610" y="1910" width="640" height="360" frameX="0" frameY="0" frameWidth="641" frameHeight="360"/>
	<SubTexture name="shot instance 10085" x="7270" y="1910" width="640" height="360" frameX="0" frameY="0" frameWidth="641" frameHeight="360"/>
</TextureAtlas>
